jupyterplot/__init__.py
jupyterplot/_nbdev.py
jupyterplot/jupyterplot.py
jupyterplot-0.0.3.dist-info/LICENSE
jupyterplot-0.0.3.dist-info/METADATA
jupyterplot-0.0.3.dist-info/WHEEL
jupyterplot-0.0.3.dist-info/entry_points.txt
jupyterplot-0.0.3.dist-info/top_level.txt
jupyterplot-0.0.3.dist-info/RECORD
