Metadata-Version: 2.1
Name: jupyterplot
Version: 0.0.3
Summary: Create real-time plots in Jupyter Notebooks.
Home-page: https://github.com/lvwerra/jupyterplot
Author: Leandro von Werra
Author-email: leandro.vonwerra@gmail.com
License: Apache Software License 2.0
Keywords: real-time,plot,jupyter,notebooks
Platform: UNKNOWN
Classifier: Development Status :: 3 - Alpha
Classifier: Intended Audience :: Developers
Classifier: License :: OSI Approved :: Apache Software License
Classifier: Natural Language :: English
Classifier: Programming Language :: Python :: 3.6
Classifier: Programming Language :: Python :: 3.7
Classifier: Programming Language :: Python :: 3.8
Requires-Python: >=3.6
Requires-Dist: lrcurve (==1.1.0)
Requires-Dist: numpy
Requires-Dist: matplotlib
